<?xml version="1.0" encoding="UTF-8"?>

<device name="leftArmBroker" type="CanBusBroker" xmlns:xi="http://www.w3.org/2001/XInclude">

    <xi:include href="./common.xml" />

    <paramlist name="buses">
        <elem name="leftArm">(FLS SLS ALS FLE ALW FLW FTLH)</elem>
        <elem name="leftLeg" >(AT)</elem>
        <elem name="rightLeg">(FT)</elem>
    </paramlist>

    <action phase="startup" level="10" type="attach">
        <paramlist name="networks">
            <!-- buses -->
            <elem name="rightLeg">can0</elem>
            <elem name="leftLeg" >can1</elem>
            <elem name="leftArm">can3</elem>
            <!-- driver nodes -->
            <elem name="AT" >ID13</elem>
            <elem name="FT" >ID14</elem>
            <elem name="FLS">ID21</elem>
            <elem name="SLS">ID22</elem>
            <elem name="ALS">ID23</elem>
            <elem name="FLE">ID24</elem>
            <elem name="ALW">ID25</elem>
            <elem name="FLW">ID26</elem>
            <!-- sensor nodes -->
            <elem name="FTLH">ID34</elem>
        </paramlist>
    </action>

    <action phase="shutdown" level="50" type="detach" />

</device>
